odoo/addons/website_sale_attribute_filter_form_submit/README.rst
odoo/addons/website_sale_attribute_filter_form_submit/__init__.py
odoo/addons/website_sale_attribute_filter_form_submit/__manifest__.py
odoo/addons/website_sale_attribute_filter_form_submit/i18n/de.po
odoo/addons/website_sale_attribute_filter_form_submit/i18n/es.po
odoo/addons/website_sale_attribute_filter_form_submit/i18n/it.po
odoo/addons/website_sale_attribute_filter_form_submit/i18n/website_sale_attribute_filter_form_submit.pot
odoo/addons/website_sale_attribute_filter_form_submit/readme/CONFIGURE.rst
odoo/addons/website_sale_attribute_filter_form_submit/readme/CONTRIBUTORS.rst
odoo/addons/website_sale_attribute_filter_form_submit/readme/DESCRIPTION.rst
odoo/addons/website_sale_attribute_filter_form_submit/readme/USAGE.rst
odoo/addons/website_sale_attribute_filter_form_submit/static/description/icon.png
odoo/addons/website_sale_attribute_filter_form_submit/static/description/index.html
odoo/addons/website_sale_attribute_filter_form_submit/static/description/manual_filter_configuration.png
odoo/addons/website_sale_attribute_filter_form_submit/static/description/manual_filter_usage.gif
odoo/addons/website_sale_attribute_filter_form_submit/static/src/js/website_sale.js
odoo/addons/website_sale_attribute_filter_form_submit/templates/assets.xml
odoo/addons/website_sale_attribute_filter_form_submit/templates/website_sale.xml
odoo14_addon_website_sale_attribute_filter_form_submit-14.0.1.0.1.dev7.dist-info/METADATA
odoo14_addon_website_sale_attribute_filter_form_submit-14.0.1.0.1.dev7.dist-info/WHEEL
odoo14_addon_website_sale_attribute_filter_form_submit-14.0.1.0.1.dev7.dist-info/top_level.txt
odoo14_addon_website_sale_attribute_filter_form_submit-14.0.1.0.1.dev7.dist-info/RECORD
